{"MACAddresses":["00:1c:f0:cb:ec:92","00:1c:f0:cb:ec:5b","00:1c:f0:cb:ec:89","00:1c:f0:cb:ec:70","00:19:5b:6c:c0:25","00:19:5b:ed:bc:68","00:19:5b:6c:c0:2a"],"TimeMs":1304919623309,"MapId":1,"00:19:5b:6c:c0:25":{"APSSID":"ravinder","APCapabilities":"[WPA-EAP-TKIP+CCMP][WPA2-EAP-TKIP+CCMP-preauth]","APFrequency":"2412","APRSSI":"-92"},"HumanTime":"Mon May 09 11:10:23 GMT+05:30 2011 11:10:23","00:1c:f0:cb:ec:92":{"APSSID":"ravinder","APCapabilities":"[WPA-EAP-TKIP+CCMP][WPA2-EAP-TKIP+CCMP-preauth]","APFrequency":"2412","APRSSI":"-62"},"00:1c:f0:cb:ec:70":{"APSSID":"ravinder","APCapabilities":"[WPA-EAP-TKIP+CCMP][WPA2-EAP-TKIP+CCMP-preauth]","APFrequency":"2412","APRSSI":"-91"},"Angle":140.73814392089844,"00:19:5b:ed:bc:68":{"APSSID":"ravinder","APCapabilities":"[WPA-EAP-TKIP+CCMP][WPA2-EAP-TKIP+CCMP-preauth]","APFrequency":"2437","APRSSI":"-88"},"00:1c:f0:cb:ec:89":{"APSSID":"ravinder","APCapabilities":"[WPA-EAP-TKIP+CCMP][WPA2-EAP-TKIP+CCMP-preauth]","APFrequency":"2437","APRSSI":"-87"},"SampleName":"s166corr","00:19:5b:6c:c0:2a":{"APSSID":"ravinder","APCapabilities":"[WPA-EAP-TKIP+CCMP][WPA2-EAP-TKIP+CCMP-preauth]","APFrequency":"2412","APRSSI":"-94"},"00:1c:f0:cb:ec:5b":{"APSSID":"ravinder","APCapabilities":"[WPA-EAP-TKIP+CCMP][WPA2-EAP-TKIP+CCMP-preauth]","APFrequency":"2437","APRSSI":"-66"},"Y":0.16070684790611267,"X":0.270772248506546}